spp/__init__.py
spp/constants.py
spp/core.py
spp/space_packet.py
spp/transport/__init__.py
spp/transport/base.py
spp/transport/udp.py
ccsds_spp-1.0.0.dist-info/LICENSE.txt
ccsds_spp-1.0.0.dist-info/METADATA
ccsds_spp-1.0.0.dist-info/WHEEL
ccsds_spp-1.0.0.dist-info/top_level.txt
ccsds_spp-1.0.0.dist-info/RECORD
